<?xml version = '1.0' encoding = 'UTF-8'?>
<TableProxyOraclev20c class="oracle.dbtools.crest.model.design.storage.oracle.v20c.TableProxyOraclev20c" name="obce" directorySegmentName="seg_0" id="58519F16-3BDF-F9D5-E6DE-0F7073B15ACD">
<createdBy>skoda</createdBy>
<createdTime>2023-10-04 12:50:14 UTC</createdTime>
<ownerDesignName>B23Z_BDAS2_SEMESTRAL_PROJECT</ownerDesignName>
<logging>YES</logging>
<partitionedRowMovement>DISABLE</partitionedRowMovement>
<temporaryChanged>false</temporaryChanged>
<accessDriverType>oracle_loader</accessDriverType>
<rejectLimit></rejectLimit>
<columnProxies itemClass="oracle.dbtools.crest.model.design.storage.oracle.v12c.ColumnProxyOraclev12c">
<ColumnProxy name="nazev" id="2651A293-B2C2-D1EE-C4BE-0A7A19DE46E1">
<createdBy>skoda</createdBy>
<createdTime>2023-10-04 12:50:14 UTC</createdTime>
<ownerDesignName>B23Z_BDAS2_SEMESTRAL_PROJECT</ownerDesignName>
</ColumnProxy>
<ColumnProxy name="stat" id="6F7735CF-6DBE-EB8D-3A28-58FD67EC570B">
<createdBy>skoda</createdBy>
<createdTime>2023-10-04 12:50:14 UTC</createdTime>
<ownerDesignName>B23Z_BDAS2_SEMESTRAL_PROJECT</ownerDesignName>
<defaultValue>&apos;CZECH REPUBLIC&apos;</defaultValue>
</ColumnProxy>
<ColumnProxy name="id_obec" id="77BC0A50-8AB5-19D3-BC97-1680C9E8F8F5">
<createdBy>skoda</createdBy>
<createdTime>2023-10-04 12:50:14 UTC</createdTime>
<ownerDesignName>B23Z_BDAS2_SEMESTRAL_PROJECT</ownerDesignName>
<autoIncrementDDL>DEFAULT_CLAUSE</autoIncrementDDL>
<defaultValue>obce_seq.nextval</defaultValue>
</ColumnProxy>
<ColumnProxy name="psc" id="97861666-71EB-FC9B-7EA8-A7957908A829">
<createdBy>skoda</createdBy>
<createdTime>2023-10-04 12:50:14 UTC</createdTime>
<ownerDesignName>B23Z_BDAS2_SEMESTRAL_PROJECT</ownerDesignName>
</ColumnProxy>
<ColumnProxy name="castobce" id="AF442FB4-D4CC-5F7B-C680-7FB45C1FC48E">
<createdBy>skoda</createdBy>
<createdTime>2023-10-04 12:50:14 UTC</createdTime>
<ownerDesignName>B23Z_BDAS2_SEMESTRAL_PROJECT</ownerDesignName>
</ColumnProxy>
</columnProxies>
<primaryKeys>
<PrimaryKey class="oracle.dbtools.crest.model.design.storage.oracle.v10g.PKProxyOraclev10g" name="obec_pk" id="5A4D1A51-FADD-6111-F8D4-8FD905459F91">
<createdBy>skoda</createdBy>
<createdTime>2023-10-04 12:50:14 UTC</createdTime>
<ownerDesignName>B23Z_BDAS2_SEMESTRAL_PROJECT</ownerDesignName>
<indexSort>SORTED</indexSort>
</PrimaryKey>
</primaryKeys>
</TableProxyOraclev20c>